MobileHelperService/__init__.py
MobileHelperService/__main__.py
MobileHelperService/api copy.py
MobileHelperService/api.py
MobileHelperService/client.py
MobileHelperService/collection.py
MobileHelperService/const.py
MobileHelperService/service.py
MobileHelperService/service_api.py
MobileHelperService/tools.py
shared/const.py
shared/host_collection.py
shared/tools.py
pih_MobileHelper-1.4983.dist-info/METADATA
pih_MobileHelper-1.4983.dist-info/WHEEL
pih_MobileHelper-1.4983.dist-info/entry_points.txt
pih_MobileHelper-1.4983.dist-info/top_level.txt
pih_MobileHelper-1.4983.dist-info/RECORD
