Metadata-Version: 2.1
Name: pih-MobileHelper
Version: 1.4983
Summary: PIH Mobile Helper library
Home-page: https://pacifichosp.com/
Author: Nikita Karachentsev
Author-email: it@pacifichosp.com
License: MIT
Requires-Dist: pih
Requires-Dist: pih-mio-content
